ftcrtool/__init__.py
ftcrtool/ftcrtool.py
ftcrtool-0.0.1.dist-info/METADATA
ftcrtool-0.0.1.dist-info/WHEEL
ftcrtool-0.0.1.dist-info/top_level.txt
ftcrtool-0.0.1.dist-info/RECORD
